{
  "video_title": "WORLD CUP ALL-TIME TOP SCORERS",
  "value_format": "goals",
  "output_filename": "wc_top_scorers.mp4",
  "theme": "glass_dark_black",
  "preview_timeframe": null,
  "source": {
    "type": "players_csv",
    "path": "sportstatsraces/data/wc_top_scorers.csv",
    "entity_col": "player",
    "period_col": "year",
    "value_col": "goals",
    "source_credit": "Source: worldfootball.net, FIFA",
    "icon_ids": {
      "Silvio Piola": "pe50067",
      "Uwe Seeler": "pe41482",
      "Pedro Cea": "pe48151",
      "André Abegglen": "pe50242",
      "Leônidas": "pe41518",
      "Edmund Conen": "pe45618",
      "Luis Monti": "pe45642",
      "Eusébio": "pe41499",
      "Jürgen Klinsmann": "pe3209",
      "Jairzinho": "pe41678",
      "Juan Anselmo": "pe48159",
      "Gary Lineker": "pe42438",
      "Manuel Rosas": "pe48088",
      "Ivan Bek": "pe48055",
      "Thomas Müller": "pe3249",
      "Guillermo Stábile": "pe41514",
      "Gerd Müller": "pe3257",
      "Oldrich Nejedly": "pe54812",
      "Josef Hügi": "pe59934",
      "Erich Probst": "pe62885",
      "Juan Schiaffino": "pe45889",
      "Miroslav Klose": "pe3205",
      "Pelé": "pe41453",
      "Sándor Kocsis": "pe41508",
      "Grzegorz Lato": "pe49490",
      "Cristiano Ronaldo": "pe18623",
      "Ademir": "pe41515",
      "Harry Kane": "pe236781",
      "Luigi Colaussi": "pe53328",
      "Lajos Tichy": "pe53459",
      "Preguinho": "pe48128",
      "André Maschinot": "pe48076",
      "Dorde Vujadinovic": "pe48060",
      "Hans Schäfer": "pe43132",
      "Max Morlock": "pe42535",
      "Kylian Mbappé": "pe366468",
      "Carlos Peucelle": "pe45643",
      "Adolfo Zumelzú": "pe45661",
      "Leopold Kielholz": "pe60369",
      "Raimundo Orsi": "pe61656",
      "Helmut Rahn": "pe41479",
      "Just Fontaine": "pe41488",
      "Gabriel Batistuta": "pe41171",
      "Teófilo Cubillas": "pe41519",
      "Bert Patenaude": "pe48024",
      "Karl-Heinz Rummenigge": "pe41480",
      "Angelo Schiavio": "pe61200",
      "Lionel Messi": "pe1757",
      "György Sárosi": "pe61123",
      "Vavá": "pe41722",
      "Gyula Zsengellér": "pe62687",
      "Ronaldo": "pe846",
      "Oscar Míguez": "pe62158"
    }
  },
  "assets": {
    "type": "headshots",
    "headshots_src_dir": "sportstatsraces/data/wc_headshots"
  },
  "render": {
    "top_n_on_screen": 10,
    "steps_per_year": 60,
    "fps": 30,
    "bitrate": 8000,
    "rank_smooth_window_a": 10,
    "rank_smooth_window_b": 15,
    "row_min_weight": 0.45,
    "flag_corner_radius_frac": 0.08,
    "show_total_trend": false,
    "race_top": 0.8,
    "race_bottom": 0.1,
    "spotlight": {
      "enabled": false
    },
    "show_row_rate": false,
    "show_retirement": true,
    "row_fade": false,
    "value_suffix": "goals",
    "show_zero_values": false,
    "header_template": "WORLD CUP TOP SCORERS",
    "header_timeline": true,
    "intro_style": "cascade",
    "font_scale": 1.0,
    "background_video": "sportstatsraces/Football Race Background.mp4",
    "narration": {
      "enabled": true,
      "tts": {
        "provider": "elevenlabs",
        "voice_id": "QpDQJR3frbDwOhTIo8nW",
        "model_id": "eleven_turbo_v2_5",
        "stability": 0.3,
        "style": 0.6,
        "similarity_boost": 0.9,
        "speed": 1.06
      },
      "tail_buffer_seconds": 1.0,
      "background_music": {
        "path": "Gridiron_Velocity_2026-07-04T142733.mp3",
        "voice_volume_db": 0.0,
        "music_volume_db": -12.0,
        "fade_in_seconds": 0.5,
        "fade_out_seconds": 1.5
      },
      "words_per_second": 3.2,
      "max_speech_coverage": 0.45,
      "min_body_seconds": 23.0,
      "tone": "excited stadium football commentator speaking VERY SIMPLE English that a 10-year-old easily understands — short sentences, common everyday words only. NO slang of any kind (banned: mate, mental, scenes, worldie, clinical, banged, y'all, bro, dude). NEVER mention the war, wartime, or any pause/break/freeze in the tournament — talk about the goalscorers and eras instead"
    },
    "timeline_label": "{year}",
    "ordinal_periods": true,
    "timeline_pop": false,
    "header_y_offset": 0.04,
    "row_retired_label": "RETIRED",
    "row_sublabels": {
      "Lionel Messi": {
        "2006": "WC 2006",
        "2010": "WC 2006",
        "2014": "WC 2006-2014",
        "2018": "WC 2006-2018",
        "2022": "WC 2006-2022",
        "2026": "WC 2006-2026"
      },
      "Kylian Mbappé": {
        "2018": "WC 2018",
        "2022": "WC 2018-2022",
        "2026": "WC 2018-2026"
      },
      "Miroslav Klose": {
        "2002": "WC 2002",
        "2006": "WC 2002-2006",
        "2010": "WC 2002-2010",
        "2014": "WC 2002-2014",
        "2018": "WC 2002-2014",
        "2022": "WC 2002-2014",
        "2026": "WC 2002-2014"
      },
      "Ronaldo": {
        "1998": "WC 1998",
        "2002": "WC 1998-2002",
        "2006": "WC 1998-2006",
        "2010": "WC 1998-2006",
        "2014": "WC 1998-2006",
        "2018": "WC 1998-2006",
        "2022": "WC 1998-2006",
        "2026": "WC 1998-2006"
      },
      "Gerd Müller": {
        "1970": "WC 1970",
        "1974": "WC 1970-1974",
        "1978": "WC 1970-1974",
        "1982": "WC 1970-1974",
        "1986": "WC 1970-1974",
        "1990": "WC 1970-1974",
        "1994": "WC 1970-1974",
        "1998": "WC 1970-1974",
        "2002": "WC 1970-1974",
        "2006": "WC 1970-1974",
        "2010": "WC 1970-1974",
        "2014": "WC 1970-1974",
        "2018": "WC 1970-1974",
        "2022": "WC 1970-1974",
        "2026": "WC 1970-1974"
      },
      "Harry Kane": {
        "2018": "WC 2018",
        "2022": "WC 2018-2022",
        "2026": "WC 2018-2026"
      },
      "Just Fontaine": {
        "1958": "WC 1958",
        "1962": "WC 1958",
        "1966": "WC 1958",
        "1970": "WC 1958",
        "1974": "WC 1958",
        "1978": "WC 1958",
        "1982": "WC 1958",
        "1986": "WC 1958",
        "1990": "WC 1958",
        "1994": "WC 1958",
        "1998": "WC 1958",
        "2002": "WC 1958",
        "2006": "WC 1958",
        "2010": "WC 1958",
        "2014": "WC 1958",
        "2018": "WC 1958",
        "2022": "WC 1958",
        "2026": "WC 1958"
      },
      "Pelé": {
        "1958": "WC 1958",
        "1962": "WC 1958-1962",
        "1966": "WC 1958-1966",
        "1970": "WC 1958-1970",
        "1974": "WC 1958-1970",
        "1978": "WC 1958-1970",
        "1982": "WC 1958-1970",
        "1986": "WC 1958-1970",
        "1990": "WC 1958-1970",
        "1994": "WC 1958-1970",
        "1998": "WC 1958-1970",
        "2002": "WC 1958-1970",
        "2006": "WC 1958-1970",
        "2010": "WC 1958-1970",
        "2014": "WC 1958-1970",
        "2018": "WC 1958-1970",
        "2022": "WC 1958-1970",
        "2026": "WC 1958-1970"
      },
      "Jürgen Klinsmann": {
        "1990": "WC 1990",
        "1994": "WC 1990-1994",
        "1998": "WC 1990-1998",
        "2002": "WC 1990-1998",
        "2006": "WC 1990-1998",
        "2010": "WC 1990-1998",
        "2014": "WC 1990-1998",
        "2018": "WC 1990-1998",
        "2022": "WC 1990-1998",
        "2026": "WC 1990-1998"
      },
      "Sándor Kocsis": {
        "1954": "WC 1954",
        "1958": "WC 1954",
        "1962": "WC 1954",
        "1966": "WC 1954",
        "1970": "WC 1954",
        "1974": "WC 1954",
        "1978": "WC 1954",
        "1982": "WC 1954",
        "1986": "WC 1954",
        "1990": "WC 1954",
        "1994": "WC 1954",
        "1998": "WC 1954",
        "2002": "WC 1954",
        "2006": "WC 1954",
        "2010": "WC 1954",
        "2014": "WC 1954",
        "2018": "WC 1954",
        "2022": "WC 1954",
        "2026": "WC 1954"
      },
      "Cristiano Ronaldo": {
        "2006": "WC 2006",
        "2010": "WC 2006-2010",
        "2014": "WC 2006-2014",
        "2018": "WC 2006-2018",
        "2022": "WC 2006-2022",
        "2026": "WC 2006-2026"
      },
      "Gary Lineker": {
        "1986": "WC 1986",
        "1990": "WC 1986-1990",
        "1994": "WC 1986-1990",
        "1998": "WC 1986-1990",
        "2002": "WC 1986-1990",
        "2006": "WC 1986-1990",
        "2010": "WC 1986-1990",
        "2014": "WC 1986-1990",
        "2018": "WC 1986-1990",
        "2022": "WC 1986-1990",
        "2026": "WC 1986-1990"
      },
      "Thomas Müller": {
        "2010": "WC 2010",
        "2014": "WC 2010-2014",
        "2018": "WC 2010-2014",
        "2022": "WC 2010-2014",
        "2026": "WC 2010-2014"
      },
      "Grzegorz Lato": {
        "1974": "WC 1974",
        "1978": "WC 1974-1978",
        "1982": "WC 1974-1982",
        "1986": "WC 1974-1982",
        "1990": "WC 1974-1982",
        "1994": "WC 1974-1982",
        "1998": "WC 1974-1982",
        "2002": "WC 1974-1982",
        "2006": "WC 1974-1982",
        "2010": "WC 1974-1982",
        "2014": "WC 1974-1982",
        "2018": "WC 1974-1982",
        "2022": "WC 1974-1982",
        "2026": "WC 1974-1982"
      },
      "Helmut Rahn": {
        "1954": "WC 1954",
        "1958": "WC 1954-1958",
        "1962": "WC 1954-1958",
        "1966": "WC 1954-1958",
        "1970": "WC 1954-1958",
        "1974": "WC 1954-1958",
        "1978": "WC 1954-1958",
        "1982": "WC 1954-1958",
        "1986": "WC 1954-1958",
        "1990": "WC 1954-1958",
        "1994": "WC 1954-1958",
        "1998": "WC 1954-1958",
        "2002": "WC 1954-1958",
        "2006": "WC 1954-1958",
        "2010": "WC 1954-1958",
        "2014": "WC 1954-1958",
        "2018": "WC 1954-1958",
        "2022": "WC 1954-1958",
        "2026": "WC 1954-1958"
      },
      "Gabriel Batistuta": {
        "1994": "WC 1994",
        "1998": "WC 1994-1998",
        "2002": "WC 1994-2002",
        "2006": "WC 1994-2002",
        "2010": "WC 1994-2002",
        "2014": "WC 1994-2002",
        "2018": "WC 1994-2002",
        "2022": "WC 1994-2002",
        "2026": "WC 1994-2002"
      },
      "Teófilo Cubillas": {
        "1970": "WC 1970",
        "1974": "WC 1970",
        "1978": "WC 1970-1978",
        "1982": "WC 1970-1978",
        "1986": "WC 1970-1978",
        "1990": "WC 1970-1978",
        "1994": "WC 1970-1978",
        "1998": "WC 1970-1978",
        "2002": "WC 1970-1978",
        "2006": "WC 1970-1978",
        "2010": "WC 1970-1978",
        "2014": "WC 1970-1978",
        "2018": "WC 1970-1978",
        "2022": "WC 1970-1978",
        "2026": "WC 1970-1978"
      },
      "Uwe Seeler": {
        "1958": "WC 1958",
        "1962": "WC 1958-1962",
        "1966": "WC 1958-1966",
        "1970": "WC 1958-1970",
        "1974": "WC 1958-1970",
        "1978": "WC 1958-1970",
        "1982": "WC 1958-1970",
        "1986": "WC 1958-1970",
        "1990": "WC 1958-1970",
        "1994": "WC 1958-1970",
        "1998": "WC 1958-1970",
        "2002": "WC 1958-1970",
        "2006": "WC 1958-1970",
        "2010": "WC 1958-1970",
        "2014": "WC 1958-1970",
        "2018": "WC 1958-1970",
        "2022": "WC 1958-1970",
        "2026": "WC 1958-1970"
      },
      "Eusébio": {
        "1966": "WC 1966",
        "1970": "WC 1966",
        "1974": "WC 1966",
        "1978": "WC 1966",
        "1982": "WC 1966",
        "1986": "WC 1966",
        "1990": "WC 1966",
        "1994": "WC 1966",
        "1998": "WC 1966",
        "2002": "WC 1966",
        "2006": "WC 1966",
        "2010": "WC 1966",
        "2014": "WC 1966",
        "2018": "WC 1966",
        "2022": "WC 1966",
        "2026": "WC 1966"
      },
      "Jairzinho": {
        "1970": "WC 1970",
        "1974": "WC 1970-1974",
        "1978": "WC 1970-1974",
        "1982": "WC 1970-1974",
        "1986": "WC 1970-1974",
        "1990": "WC 1970-1974",
        "1994": "WC 1970-1974",
        "1998": "WC 1970-1974",
        "2002": "WC 1970-1974",
        "2006": "WC 1970-1974",
        "2010": "WC 1970-1974",
        "2014": "WC 1970-1974",
        "2018": "WC 1970-1974",
        "2022": "WC 1970-1974",
        "2026": "WC 1970-1974"
      },
      "Ademir": {
        "1950": "WC 1950",
        "1954": "WC 1950",
        "1958": "WC 1950",
        "1962": "WC 1950",
        "1966": "WC 1950",
        "1970": "WC 1950",
        "1974": "WC 1950",
        "1978": "WC 1950",
        "1982": "WC 1950",
        "1986": "WC 1950",
        "1990": "WC 1950",
        "1994": "WC 1950",
        "1998": "WC 1950",
        "2002": "WC 1950",
        "2006": "WC 1950",
        "2010": "WC 1950",
        "2014": "WC 1950",
        "2018": "WC 1950",
        "2022": "WC 1950",
        "2026": "WC 1950"
      },
      "Karl-Heinz Rummenigge": {
        "1978": "WC 1978",
        "1982": "WC 1978-1982",
        "1986": "WC 1978-1986",
        "1990": "WC 1978-1986",
        "1994": "WC 1978-1986",
        "1998": "WC 1978-1986",
        "2002": "WC 1978-1986",
        "2006": "WC 1978-1986",
        "2010": "WC 1978-1986",
        "2014": "WC 1978-1986",
        "2018": "WC 1978-1986",
        "2022": "WC 1978-1986",
        "2026": "WC 1978-1986"
      },
      "Vavá": {
        "1958": "WC 1958",
        "1962": "WC 1958-1962",
        "1966": "WC 1958-1962",
        "1970": "WC 1958-1962",
        "1974": "WC 1958-1962",
        "1978": "WC 1958-1962",
        "1982": "WC 1958-1962",
        "1986": "WC 1958-1962",
        "1990": "WC 1958-1962",
        "1994": "WC 1958-1962",
        "1998": "WC 1958-1962",
        "2002": "WC 1958-1962",
        "2006": "WC 1958-1962",
        "2010": "WC 1958-1962",
        "2014": "WC 1958-1962",
        "2018": "WC 1958-1962",
        "2022": "WC 1958-1962",
        "2026": "WC 1958-1962"
      },
      "Leônidas": {
        "1934": "WC 1934",
        "1938": "WC 1934-1938",
        "1950": "WC 1934-1938",
        "1954": "WC 1934-1938",
        "1958": "WC 1934-1938",
        "1962": "WC 1934-1938",
        "1966": "WC 1934-1938",
        "1970": "WC 1934-1938",
        "1974": "WC 1934-1938",
        "1978": "WC 1934-1938",
        "1982": "WC 1934-1938",
        "1986": "WC 1934-1938",
        "1990": "WC 1934-1938",
        "1994": "WC 1934-1938",
        "1998": "WC 1934-1938",
        "2002": "WC 1934-1938",
        "2006": "WC 1934-1938",
        "2010": "WC 1934-1938",
        "2014": "WC 1934-1938",
        "2018": "WC 1934-1938",
        "2022": "WC 1934-1938",
        "2026": "WC 1934-1938"
      },
      "Guillermo Stábile": {
        "1930": "WC 1930",
        "1934": "WC 1930",
        "1938": "WC 1930",
        "1950": "WC 1930",
        "1954": "WC 1930",
        "1958": "WC 1930",
        "1962": "WC 1930",
        "1966": "WC 1930",
        "1970": "WC 1930",
        "1974": "WC 1930",
        "1978": "WC 1930",
        "1982": "WC 1930",
        "1986": "WC 1930",
        "1990": "WC 1930",
        "1994": "WC 1930",
        "1998": "WC 1930",
        "2002": "WC 1930",
        "2006": "WC 1930",
        "2010": "WC 1930",
        "2014": "WC 1930",
        "2018": "WC 1930",
        "2022": "WC 1930",
        "2026": "WC 1930"
      },
      "Oscar Míguez": {
        "1950": "WC 1950",
        "1954": "WC 1950-1954",
        "1958": "WC 1950-1954",
        "1962": "WC 1950-1954",
        "1966": "WC 1950-1954",
        "1970": "WC 1950-1954",
        "1974": "WC 1950-1954",
        "1978": "WC 1950-1954",
        "1982": "WC 1950-1954",
        "1986": "WC 1950-1954",
        "1990": "WC 1950-1954",
        "1994": "WC 1950-1954",
        "1998": "WC 1950-1954",
        "2002": "WC 1950-1954",
        "2006": "WC 1950-1954",
        "2010": "WC 1950-1954",
        "2014": "WC 1950-1954",
        "2018": "WC 1950-1954",
        "2022": "WC 1950-1954",
        "2026": "WC 1950-1954"
      },
      "Oldrich Nejedly": {
        "1934": "WC 1934",
        "1938": "WC 1934-1938",
        "1950": "WC 1934-1938",
        "1954": "WC 1934-1938",
        "1958": "WC 1934-1938",
        "1962": "WC 1934-1938",
        "1966": "WC 1934-1938",
        "1970": "WC 1934-1938",
        "1974": "WC 1934-1938",
        "1978": "WC 1934-1938",
        "1982": "WC 1934-1938",
        "1986": "WC 1934-1938",
        "1990": "WC 1934-1938",
        "1994": "WC 1934-1938",
        "1998": "WC 1934-1938",
        "2002": "WC 1934-1938",
        "2006": "WC 1934-1938",
        "2010": "WC 1934-1938",
        "2014": "WC 1934-1938",
        "2018": "WC 1934-1938",
        "2022": "WC 1934-1938",
        "2026": "WC 1934-1938"
      },
      "Lajos Tichy": {
        "1958": "WC 1958",
        "1962": "WC 1958-1962",
        "1966": "WC 1958-1962",
        "1970": "WC 1958-1962",
        "1974": "WC 1958-1962",
        "1978": "WC 1958-1962",
        "1982": "WC 1958-1962",
        "1986": "WC 1958-1962",
        "1990": "WC 1958-1962",
        "1994": "WC 1958-1962",
        "1998": "WC 1958-1962",
        "2002": "WC 1958-1962",
        "2006": "WC 1958-1962",
        "2010": "WC 1958-1962",
        "2014": "WC 1958-1962",
        "2018": "WC 1958-1962",
        "2022": "WC 1958-1962",
        "2026": "WC 1958-1962"
      },
      "Hans Schäfer": {
        "1954": "WC 1954",
        "1958": "WC 1954-1958",
        "1962": "WC 1954-1958",
        "1966": "WC 1954-1958",
        "1970": "WC 1954-1958",
        "1974": "WC 1954-1958",
        "1978": "WC 1954-1958",
        "1982": "WC 1954-1958",
        "1986": "WC 1954-1958",
        "1990": "WC 1954-1958",
        "1994": "WC 1954-1958",
        "1998": "WC 1954-1958",
        "2002": "WC 1954-1958",
        "2006": "WC 1954-1958",
        "2010": "WC 1954-1958",
        "2014": "WC 1954-1958",
        "2018": "WC 1954-1958",
        "2022": "WC 1954-1958",
        "2026": "WC 1954-1958"
      },
      "Josef Hügi": {
        "1954": "WC 1954",
        "1958": "WC 1954",
        "1962": "WC 1954",
        "1966": "WC 1954",
        "1970": "WC 1954",
        "1974": "WC 1954",
        "1978": "WC 1954",
        "1982": "WC 1954",
        "1986": "WC 1954",
        "1990": "WC 1954",
        "1994": "WC 1954",
        "1998": "WC 1954",
        "2002": "WC 1954",
        "2006": "WC 1954",
        "2010": "WC 1954",
        "2014": "WC 1954",
        "2018": "WC 1954",
        "2022": "WC 1954",
        "2026": "WC 1954"
      },
      "Erich Probst": {
        "1954": "WC 1954",
        "1958": "WC 1954",
        "1962": "WC 1954",
        "1966": "WC 1954",
        "1970": "WC 1954",
        "1974": "WC 1954",
        "1978": "WC 1954",
        "1982": "WC 1954",
        "1986": "WC 1954",
        "1990": "WC 1954",
        "1994": "WC 1954",
        "1998": "WC 1954",
        "2002": "WC 1954",
        "2006": "WC 1954",
        "2010": "WC 1954",
        "2014": "WC 1954",
        "2018": "WC 1954",
        "2022": "WC 1954",
        "2026": "WC 1954"
      },
      "Max Morlock": {
        "1954": "WC 1954",
        "1958": "WC 1954",
        "1962": "WC 1954",
        "1966": "WC 1954",
        "1970": "WC 1954",
        "1974": "WC 1954",
        "1978": "WC 1954",
        "1982": "WC 1954",
        "1986": "WC 1954",
        "1990": "WC 1954",
        "1994": "WC 1954",
        "1998": "WC 1954",
        "2002": "WC 1954",
        "2006": "WC 1954",
        "2010": "WC 1954",
        "2014": "WC 1954",
        "2018": "WC 1954",
        "2022": "WC 1954",
        "2026": "WC 1954"
      },
      "György Sárosi": {
        "1934": "WC 1934",
        "1938": "WC 1934-1938",
        "1950": "WC 1934-1938",
        "1954": "WC 1934-1938",
        "1958": "WC 1934-1938",
        "1962": "WC 1934-1938",
        "1966": "WC 1934-1938",
        "1970": "WC 1934-1938",
        "1974": "WC 1934-1938",
        "1978": "WC 1934-1938",
        "1982": "WC 1934-1938",
        "1986": "WC 1934-1938",
        "1990": "WC 1934-1938",
        "1994": "WC 1934-1938",
        "1998": "WC 1934-1938",
        "2002": "WC 1934-1938",
        "2006": "WC 1934-1938",
        "2010": "WC 1934-1938",
        "2014": "WC 1934-1938",
        "2018": "WC 1934-1938",
        "2022": "WC 1934-1938",
        "2026": "WC 1934-1938"
      },
      "Silvio Piola": {
        "1938": "WC 1938",
        "1950": "WC 1938",
        "1954": "WC 1938",
        "1958": "WC 1938",
        "1962": "WC 1938",
        "1966": "WC 1938",
        "1970": "WC 1938",
        "1974": "WC 1938",
        "1978": "WC 1938",
        "1982": "WC 1938",
        "1986": "WC 1938",
        "1990": "WC 1938",
        "1994": "WC 1938",
        "1998": "WC 1938",
        "2002": "WC 1938",
        "2006": "WC 1938",
        "2010": "WC 1938",
        "2014": "WC 1938",
        "2018": "WC 1938",
        "2022": "WC 1938",
        "2026": "WC 1938"
      },
      "Pedro Cea": {
        "1930": "WC 1930",
        "1934": "WC 1930",
        "1938": "WC 1930",
        "1950": "WC 1930",
        "1954": "WC 1930",
        "1958": "WC 1930",
        "1962": "WC 1930",
        "1966": "WC 1930",
        "1970": "WC 1930",
        "1974": "WC 1930",
        "1978": "WC 1930",
        "1982": "WC 1930",
        "1986": "WC 1930",
        "1990": "WC 1930",
        "1994": "WC 1930",
        "1998": "WC 1930",
        "2002": "WC 1930",
        "2006": "WC 1930",
        "2010": "WC 1930",
        "2014": "WC 1930",
        "2018": "WC 1930",
        "2022": "WC 1930",
        "2026": "WC 1930"
      },
      "Juan Schiaffino": {
        "1950": "WC 1950",
        "1954": "WC 1950-1954",
        "1958": "WC 1950-1954",
        "1962": "WC 1950-1954",
        "1966": "WC 1950-1954",
        "1970": "WC 1950-1954",
        "1974": "WC 1950-1954",
        "1978": "WC 1950-1954",
        "1982": "WC 1950-1954",
        "1986": "WC 1950-1954",
        "1990": "WC 1950-1954",
        "1994": "WC 1950-1954",
        "1998": "WC 1950-1954",
        "2002": "WC 1950-1954",
        "2006": "WC 1950-1954",
        "2010": "WC 1950-1954",
        "2014": "WC 1950-1954",
        "2018": "WC 1950-1954",
        "2022": "WC 1950-1954",
        "2026": "WC 1950-1954"
      },
      "Gyula Zsengellér": {
        "1938": "WC 1938",
        "1950": "WC 1938",
        "1954": "WC 1938",
        "1958": "WC 1938",
        "1962": "WC 1938",
        "1966": "WC 1938",
        "1970": "WC 1938",
        "1974": "WC 1938",
        "1978": "WC 1938",
        "1982": "WC 1938",
        "1986": "WC 1938",
        "1990": "WC 1938",
        "1994": "WC 1938",
        "1998": "WC 1938",
        "2002": "WC 1938",
        "2006": "WC 1938",
        "2010": "WC 1938",
        "2014": "WC 1938",
        "2018": "WC 1938",
        "2022": "WC 1938",
        "2026": "WC 1938"
      },
      "André Abegglen": {
        "1934": "WC 1934",
        "1938": "WC 1934-1938",
        "1950": "WC 1934-1938",
        "1954": "WC 1934-1938",
        "1958": "WC 1934-1938",
        "1962": "WC 1934-1938",
        "1966": "WC 1934-1938",
        "1970": "WC 1934-1938",
        "1974": "WC 1934-1938",
        "1978": "WC 1934-1938",
        "1982": "WC 1934-1938",
        "1986": "WC 1934-1938",
        "1990": "WC 1934-1938",
        "1994": "WC 1934-1938",
        "1998": "WC 1934-1938",
        "2002": "WC 1934-1938",
        "2006": "WC 1934-1938",
        "2010": "WC 1934-1938",
        "2014": "WC 1934-1938",
        "2018": "WC 1934-1938",
        "2022": "WC 1934-1938",
        "2026": "WC 1934-1938"
      },
      "Edmund Conen": {
        "1934": "WC 1934",
        "1938": "WC 1934",
        "1950": "WC 1934",
        "1954": "WC 1934",
        "1958": "WC 1934",
        "1962": "WC 1934",
        "1966": "WC 1934",
        "1970": "WC 1934",
        "1974": "WC 1934",
        "1978": "WC 1934",
        "1982": "WC 1934",
        "1986": "WC 1934",
        "1990": "WC 1934",
        "1994": "WC 1934",
        "1998": "WC 1934",
        "2002": "WC 1934",
        "2006": "WC 1934",
        "2010": "WC 1934",
        "2014": "WC 1934",
        "2018": "WC 1934",
        "2022": "WC 1934",
        "2026": "WC 1934"
      },
      "Luigi Colaussi": {
        "1938": "WC 1938",
        "1950": "WC 1938",
        "1954": "WC 1938",
        "1958": "WC 1938",
        "1962": "WC 1938",
        "1966": "WC 1938",
        "1970": "WC 1938",
        "1974": "WC 1938",
        "1978": "WC 1938",
        "1982": "WC 1938",
        "1986": "WC 1938",
        "1990": "WC 1938",
        "1994": "WC 1938",
        "1998": "WC 1938",
        "2002": "WC 1938",
        "2006": "WC 1938",
        "2010": "WC 1938",
        "2014": "WC 1938",
        "2018": "WC 1938",
        "2022": "WC 1938",
        "2026": "WC 1938"
      },
      "Bert Patenaude": {
        "1930": "WC 1930",
        "1934": "WC 1930",
        "1938": "WC 1930",
        "1950": "WC 1930",
        "1954": "WC 1930",
        "1958": "WC 1930",
        "1962": "WC 1930",
        "1966": "WC 1930",
        "1970": "WC 1930",
        "1974": "WC 1930",
        "1978": "WC 1930",
        "1982": "WC 1930",
        "1986": "WC 1930",
        "1990": "WC 1930",
        "1994": "WC 1930",
        "1998": "WC 1930",
        "2002": "WC 1930",
        "2006": "WC 1930",
        "2010": "WC 1930",
        "2014": "WC 1930",
        "2018": "WC 1930",
        "2022": "WC 1930",
        "2026": "WC 1930"
      },
      "Angelo Schiavio": {
        "1934": "WC 1934",
        "1938": "WC 1934",
        "1950": "WC 1934",
        "1954": "WC 1934",
        "1958": "WC 1934",
        "1962": "WC 1934",
        "1966": "WC 1934",
        "1970": "WC 1934",
        "1974": "WC 1934",
        "1978": "WC 1934",
        "1982": "WC 1934",
        "1986": "WC 1934",
        "1990": "WC 1934",
        "1994": "WC 1934",
        "1998": "WC 1934",
        "2002": "WC 1934",
        "2006": "WC 1934",
        "2010": "WC 1934",
        "2014": "WC 1934",
        "2018": "WC 1934",
        "2022": "WC 1934",
        "2026": "WC 1934"
      },
      "Juan Anselmo": {
        "1930": "WC 1930",
        "1934": "WC 1930",
        "1938": "WC 1930",
        "1950": "WC 1930",
        "1954": "WC 1930",
        "1958": "WC 1930",
        "1962": "WC 1930",
        "1966": "WC 1930",
        "1970": "WC 1930",
        "1974": "WC 1930",
        "1978": "WC 1930",
        "1982": "WC 1930",
        "1986": "WC 1930",
        "1990": "WC 1930",
        "1994": "WC 1930",
        "1998": "WC 1930",
        "2002": "WC 1930",
        "2006": "WC 1930",
        "2010": "WC 1930",
        "2014": "WC 1930",
        "2018": "WC 1930",
        "2022": "WC 1930",
        "2026": "WC 1930"
      },
      "Ivan Bek": {
        "1930": "WC 1930",
        "1934": "WC 1930",
        "1938": "WC 1930",
        "1950": "WC 1930",
        "1954": "WC 1930",
        "1958": "WC 1930",
        "1962": "WC 1930",
        "1966": "WC 1930",
        "1970": "WC 1930",
        "1974": "WC 1930",
        "1978": "WC 1930",
        "1982": "WC 1930",
        "1986": "WC 1930",
        "1990": "WC 1930",
        "1994": "WC 1930",
        "1998": "WC 1930",
        "2002": "WC 1930",
        "2006": "WC 1930",
        "2010": "WC 1930",
        "2014": "WC 1930",
        "2018": "WC 1930",
        "2022": "WC 1930",
        "2026": "WC 1930"
      },
      "Preguinho": {
        "1930": "WC 1930",
        "1934": "WC 1930",
        "1938": "WC 1930",
        "1950": "WC 1930",
        "1954": "WC 1930",
        "1958": "WC 1930",
        "1962": "WC 1930",
        "1966": "WC 1930",
        "1970": "WC 1930",
        "1974": "WC 1930",
        "1978": "WC 1930",
        "1982": "WC 1930",
        "1986": "WC 1930",
        "1990": "WC 1930",
        "1994": "WC 1930",
        "1998": "WC 1930",
        "2002": "WC 1930",
        "2006": "WC 1930",
        "2010": "WC 1930",
        "2014": "WC 1930",
        "2018": "WC 1930",
        "2022": "WC 1930",
        "2026": "WC 1930"
      },
      "Carlos Peucelle": {
        "1930": "WC 1930",
        "1934": "WC 1930",
        "1938": "WC 1930",
        "1950": "WC 1930",
        "1954": "WC 1930",
        "1958": "WC 1930",
        "1962": "WC 1930",
        "1966": "WC 1930",
        "1970": "WC 1930",
        "1974": "WC 1930",
        "1978": "WC 1930",
        "1982": "WC 1930",
        "1986": "WC 1930",
        "1990": "WC 1930",
        "1994": "WC 1930",
        "1998": "WC 1930",
        "2002": "WC 1930",
        "2006": "WC 1930",
        "2010": "WC 1930",
        "2014": "WC 1930",
        "2018": "WC 1930",
        "2022": "WC 1930",
        "2026": "WC 1930"
      },
      "Leopold Kielholz": {
        "1934": "WC 1934",
        "1938": "WC 1934",
        "1950": "WC 1934",
        "1954": "WC 1934",
        "1958": "WC 1934",
        "1962": "WC 1934",
        "1966": "WC 1934",
        "1970": "WC 1934",
        "1974": "WC 1934",
        "1978": "WC 1934",
        "1982": "WC 1934",
        "1986": "WC 1934",
        "1990": "WC 1934",
        "1994": "WC 1934",
        "1998": "WC 1934",
        "2002": "WC 1934",
        "2006": "WC 1934",
        "2010": "WC 1934",
        "2014": "WC 1934",
        "2018": "WC 1934",
        "2022": "WC 1934",
        "2026": "WC 1934"
      },
      "Raimundo Orsi": {
        "1934": "WC 1934",
        "1938": "WC 1934",
        "1950": "WC 1934",
        "1954": "WC 1934",
        "1958": "WC 1934",
        "1962": "WC 1934",
        "1966": "WC 1934",
        "1970": "WC 1934",
        "1974": "WC 1934",
        "1978": "WC 1934",
        "1982": "WC 1934",
        "1986": "WC 1934",
        "1990": "WC 1934",
        "1994": "WC 1934",
        "1998": "WC 1934",
        "2002": "WC 1934",
        "2006": "WC 1934",
        "2010": "WC 1934",
        "2014": "WC 1934",
        "2018": "WC 1934",
        "2022": "WC 1934",
        "2026": "WC 1934"
      },
      "Luis Monti": {
        "1930": "WC 1930",
        "1934": "WC 1930",
        "1938": "WC 1930",
        "1950": "WC 1930",
        "1954": "WC 1930",
        "1958": "WC 1930",
        "1962": "WC 1930",
        "1966": "WC 1930",
        "1970": "WC 1930",
        "1974": "WC 1930",
        "1978": "WC 1930",
        "1982": "WC 1930",
        "1986": "WC 1930",
        "1990": "WC 1930",
        "1994": "WC 1930",
        "1998": "WC 1930",
        "2002": "WC 1930",
        "2006": "WC 1930",
        "2010": "WC 1930",
        "2014": "WC 1930",
        "2018": "WC 1930",
        "2022": "WC 1930",
        "2026": "WC 1930"
      },
      "Manuel Rosas": {
        "1930": "WC 1930",
        "1934": "WC 1930",
        "1938": "WC 1930",
        "1950": "WC 1930",
        "1954": "WC 1930",
        "1958": "WC 1930",
        "1962": "WC 1930",
        "1966": "WC 1930",
        "1970": "WC 1930",
        "1974": "WC 1930",
        "1978": "WC 1930",
        "1982": "WC 1930",
        "1986": "WC 1930",
        "1990": "WC 1930",
        "1994": "WC 1930",
        "1998": "WC 1930",
        "2002": "WC 1930",
        "2006": "WC 1930",
        "2010": "WC 1930",
        "2014": "WC 1930",
        "2018": "WC 1930",
        "2022": "WC 1930",
        "2026": "WC 1930"
      },
      "André Maschinot": {
        "1930": "WC 1930",
        "1934": "WC 1930",
        "1938": "WC 1930",
        "1950": "WC 1930",
        "1954": "WC 1930",
        "1958": "WC 1930",
        "1962": "WC 1930",
        "1966": "WC 1930",
        "1970": "WC 1930",
        "1974": "WC 1930",
        "1978": "WC 1930",
        "1982": "WC 1930",
        "1986": "WC 1930",
        "1990": "WC 1930",
        "1994": "WC 1930",
        "1998": "WC 1930",
        "2002": "WC 1930",
        "2006": "WC 1930",
        "2010": "WC 1930",
        "2014": "WC 1930",
        "2018": "WC 1930",
        "2022": "WC 1930",
        "2026": "WC 1930"
      },
      "Dorde Vujadinovic": {
        "1930": "WC 1930",
        "1934": "WC 1930",
        "1938": "WC 1930",
        "1950": "WC 1930",
        "1954": "WC 1930",
        "1958": "WC 1930",
        "1962": "WC 1930",
        "1966": "WC 1930",
        "1970": "WC 1930",
        "1974": "WC 1930",
        "1978": "WC 1930",
        "1982": "WC 1930",
        "1986": "WC 1930",
        "1990": "WC 1930",
        "1994": "WC 1930",
        "1998": "WC 1930",
        "2002": "WC 1930",
        "2006": "WC 1930",
        "2010": "WC 1930",
        "2014": "WC 1930",
        "2018": "WC 1930",
        "2022": "WC 1930",
        "2026": "WC 1930"
      },
      "Adolfo Zumelzú": {
        "1930": "WC 1930",
        "1934": "WC 1930",
        "1938": "WC 1930",
        "1950": "WC 1930",
        "1954": "WC 1930",
        "1958": "WC 1930",
        "1962": "WC 1930",
        "1966": "WC 1930",
        "1970": "WC 1930",
        "1974": "WC 1930",
        "1978": "WC 1930",
        "1982": "WC 1930",
        "1986": "WC 1930",
        "1990": "WC 1930",
        "1994": "WC 1930",
        "1998": "WC 1930",
        "2002": "WC 1930",
        "2006": "WC 1930",
        "2010": "WC 1930",
        "2014": "WC 1930",
        "2018": "WC 1930",
        "2022": "WC 1930",
        "2026": "WC 1930"
      }
    }
  }
}